jupyter_interactive/__init__.py
jupyter_interactive-0.1.2.dist-info/METADATA
jupyter_interactive-0.1.2.dist-info/WHEEL
jupyter_interactive-0.1.2.dist-info/RECORD
