Metadata-Version: 2.1
Name: jupyter-interactive
Version: 0.1.2
Summary: Initialise a Jupyter notebook with useful extensions and reasonable defaults
License: CC0-1.0
Author: kxmh42
Author-email: kxmh42@users.noreply.github.com
Requires-Python: >=3.8,<3.12
Classifier: License :: CC0 1.0 Universal (CC0 1.0) Public Domain Dedication
Classifier: Programming Language :: Python :: 3
Classifier: Programming Language :: Python :: 3.8
Classifier: Programming Language :: Python :: 3.9
Classifier: Programming Language :: Python :: 3.10
Classifier: Programming Language :: Python :: 3.11
Provides-Extra: tensorflow
Provides-Extra: torch
Requires-Dist: coconut (>=3.0.2,<4.0.0)
Requires-Dist: ipykernel (>=6.29.0,<7.0.0)
Requires-Dist: ipympl (>=0.9.3,<0.10.0)
Requires-Dist: ipython-autoimport (>=0.4,<0.5)
Requires-Dist: itables (>=1.5.3,<2.0.0)
Requires-Dist: matplotlib-inline (>=0.1.6,<0.2.0)
Requires-Dist: numpy (>=1.22,<2.0)
Requires-Dist: pandas (>=1.3)
Requires-Dist: plotly (>=5.15.0,<6.0.0)
Requires-Dist: polars (>=0.18.2,<0.19.0)
Requires-Dist: rpy2 (>=3.5.12)
Requires-Dist: tensorflow (>=2.12,<3.0) ; extra == "tensorflow"
Requires-Dist: torch (>=1.13,<2.0) ; extra == "torch"
